xkbgroup/__init__.py
xkbgroup/__main__.py
xkbgroup/core.py
xkbgroup/test.py
xkbgroup/version.py
xkbgroup/xkb.py
xkbgroup-0.2.0.dist-info/DESCRIPTION.rst
xkbgroup-0.2.0.dist-info/METADATA
xkbgroup-0.2.0.dist-info/RECORD
xkbgroup-0.2.0.dist-info/WHEEL
xkbgroup-0.2.0.dist-info/entry_points.txt
xkbgroup-0.2.0.dist-info/metadata.json
xkbgroup-0.2.0.dist-info/top_level.txt
xkbgroup-0.2.0.dist-info/zip-safe
